XBee-2.3.2.dist-info/DESCRIPTION.rst
XBee-2.3.2.dist-info/METADATA
XBee-2.3.2.dist-info/RECORD
XBee-2.3.2.dist-info/WHEEL
XBee-2.3.2.dist-info/metadata.json
XBee-2.3.2.dist-info/top_level.txt
xbee/__init__.py
xbee/frame.py
xbee/python2to3.py
xbee/backend/__init__.py
xbee/backend/base.py
xbee/backend/digimesh.py
xbee/backend/ieee.py
xbee/backend/zigbee.py
xbee/helpers/__init__.py
xbee/helpers/dispatch/__init__.py
xbee/helpers/dispatch/dispatch.py
xbee/thread/__init__.py
xbee/thread/base.py
xbee/thread/digimesh.py
xbee/thread/ieee.py
xbee/thread/zigbee.py
xbee/tornado/__init__.py
xbee/tornado/base.py
xbee/tornado/digimesh.py
xbee/tornado/ieee.py
xbee/tornado/zigbee.py
