Metadata-Version: 1.1
Name: XBee
Version: 2.3.2
Summary: Python tools for working with XBee radios
Home-page: https://github.com/nioinnovation/python-xbee
Author: n.io
Author-email: info@n.io
License: MIT
Platform: UNKNOWN
Classifier: Development Status :: 5 - Production/Stable
Classifier: Intended Audience :: Developers
Classifier: License :: OSI Approved :: MIT License
Classifier: Topic :: Terminals :: Serial
Classifier: Programming Language :: Python
Classifier: Programming Language :: Python :: 2
Classifier: Programming Language :: Python :: 3
